kwextractor/__init__.py
kwextractor/constants.py
kwextractor/version.py
kwextractor/data/data_emotion_words.txt
kwextractor/data/data_full_allkeywords.txt
kwextractor/data/stop_words_vn_tokenized.txt
kwextractor/process/__init__.py
kwextractor/process/extract_keywords.py
kwextractor/process/extract_numverse.py
kwextractor/process/replacing_w2n.py
kwextractor/utils/__init__.py
kwextractor/utils/process_kw.py
kwextractor-0.0.8.dist-info/METADATA
kwextractor-0.0.8.dist-info/WHEEL
kwextractor-0.0.8.dist-info/top_level.txt
kwextractor-0.0.8.dist-info/RECORD
