Metadata-Version: 2.1
Name: kwextractor
Version: 0.0.8
Summary: Extract keywords for vietnamese text.
Author: Trinh Do Duy Hung
Author-email: trinhhungsss492@gmail.com
License: MIT
Requires-Dist: underthesea
Requires-Dist: vietnam-number
Requires-Dist: scikit-learn
Requires-Dist: yake
Requires-Dist: rapidfuzz
